src/__init__.py
src/client.py
src/lm.py
lm_cli-0.1.6.dist-info/METADATA
lm_cli-0.1.6.dist-info/WHEEL
lm_cli-0.1.6.dist-info/entry_points.txt
lm_cli-0.1.6.dist-info/top_level.txt
lm_cli-0.1.6.dist-info/RECORD
