Metadata-Version: 2.1
Name: lm-cli
Version: 0.1.6
Summary: cli for dkube license manager
Home-page: https://github.com/oneconvergence/license-manager
Author: Authors @ One Convergence
Author-email: manju.vikash145@gmail.com
License: UNKNOWN
Platform: UNKNOWN
Classifier: Programming Language :: Python :: 3
Classifier: Programming Language :: Python :: 3.7
Classifier: Operating System :: OS Independent
Requires-Python: >=3
Requires-Dist: Click
Requires-Dist: prettytable (<=2.1.0,>=1.0.0)
Requires-Dist: requests (==2.25.1)
